{"version":1,"resource":"file:///home/albys/.Xresources","entries":[{"id":"hAZ7","timestamp":1653155274167},{"id":"Avma","timestamp":1653155504111},{"id":"ojCU","timestamp":1653155522874},{"id":"Wfje","timestamp":1653155539837},{"id":"lpva","timestamp":1653156174682},{"id":"0dwp","timestamp":1653156272155},{"id":"VM6w","timestamp":1653156287402},{"id":"nLbM","timestamp":1653156346195},{"id":"fl8d","timestamp":1653156366053},{"id":"Ukd1","timestamp":1653248191865},{"id":"WGfA","timestamp":1653248245847}]}